suorafxctl.py
suorafxctl-1.0.2.dist-info/LICENSE
suorafxctl-1.0.2.dist-info/METADATA
suorafxctl-1.0.2.dist-info/WHEEL
suorafxctl-1.0.2.dist-info/entry_points.txt
suorafxctl-1.0.2.dist-info/top_level.txt
suorafxctl-1.0.2.dist-info/RECORD
