Metadata-Version: 2.1
Name: suorafxctl
Version: 1.0.2
Summary: Configure Roccat Suora FX keyboards on Linux
Home-page: https://github.com/flozz/suorafxctl
Author: Fabien LOISON
License: WTFPL
Keywords: roccat suora suorafx keyboard
Platform: Linux
License-File: LICENSE
Requires-Dist: libusb1>=2.0.0
Requires-Dist: setuptools
Provides-Extra: dev
Requires-Dist: nox; extra == "dev"
Requires-Dist: flake8; extra == "dev"
Requires-Dist: black; extra == "dev"
